intersystems_iris/_BufferReader.py
intersystems_iris/_BufferWriter.py
intersystems_iris/_ConnectionInformation.py
intersystems_iris/_ConnectionParameters.py
intersystems_iris/_Constant.py
intersystems_iris/_DBList.py
intersystems_iris/_Device.py
intersystems_iris/_GatewayContext.py
intersystems_iris/_GatewayException.py
intersystems_iris/_GatewayUtility.py
intersystems_iris/_IRIS.py
intersystems_iris/_IRISConnection.py
intersystems_iris/_IRISEmbedded.py
intersystems_iris/_IRISGlobalNode.py
intersystems_iris/_IRISGlobalNodeView.py
intersystems_iris/_IRISIterator.py
intersystems_iris/_IRISList.py
intersystems_iris/_IRISNative.py
intersystems_iris/_IRISOREF.py
intersystems_iris/_IRISObject.py
intersystems_iris/_IRISReference.py
intersystems_iris/_InStream.py
intersystems_iris/_LegacyIterator.py
intersystems_iris/_ListItem.py
intersystems_iris/_ListReader.py
intersystems_iris/_ListWriter.py
intersystems_iris/_LogFileStream.py
intersystems_iris/_MessageHeader.py
intersystems_iris/_OutStream.py
intersystems_iris/_PrintStream.py
intersystems_iris/_PythonGateway.py
intersystems_iris/_SharedMemorySocket.py
intersystems_iris/__init__.py
intersystems_iris/__main__.py
intersystems_iris/dbapi/_Column.py
intersystems_iris/dbapi/_DBAPI.py
intersystems_iris/dbapi/_Descriptor.py
intersystems_iris/dbapi/_IRISStream.py
intersystems_iris/dbapi/_Message.py
intersystems_iris/dbapi/_Parameter.py
intersystems_iris/dbapi/_ParameterCollection.py
intersystems_iris/dbapi/_ResultSetRow.py
intersystems_iris/dbapi/_SQLType.py
intersystems_iris/dbapi/__init__.py
intersystems_iris/dbapi/preparser/_PreParser.py
intersystems_iris/dbapi/preparser/_Scanner.py
intersystems_iris/dbapi/preparser/_Token.py
intersystems_iris/dbapi/preparser/_TokenList.py
intersystems_iris/dbapi/preparser/__init__.py
intersystems_iris/pex/_BusinessHost.py
intersystems_iris/pex/_BusinessOperation.py
intersystems_iris/pex/_BusinessProcess.py
intersystems_iris/pex/_BusinessService.py
intersystems_iris/pex/_Common.py
sqlalchemy_iris-0.18.0.dist-info/licenses/LICENSE
sqlalchemy_iris-0.18.0.dist-info/METADATA
sqlalchemy_iris-0.18.0.dist-info/WHEEL
sqlalchemy_iris-0.18.0.dist-info/entry_points.txt
sqlalchemy_iris-0.18.0.dist-info/top_level.txt
sqlalchemy_iris-0.18.0.dist-info/RECORD
