Metadata-Version: 2.4
Name: sqlalchemy-iris
Version: 0.18.0
Summary: InterSystems IRIS for SQLAlchemy
Home-page: https://github.com/caretdev/sqlalchemy-iris
Maintainer: CaretDev
Maintainer-email: dmitry@caretdev.com
License: MIT
Project-URL: Source, https://github.com/caretdev/sqlalchemy-iris
Project-URL: Tracker, https://github.com/caretdev/sqlalchemy-iris/issues
Keywords: "SQLAlchemy InterSystems IRIS"
Classifier: Development Status :: 4 - Beta
Classifier: Intended Audience :: Developers
Classifier: License :: OSI Approved :: MIT License
Classifier: Programming Language :: Python
Classifier: Programming Language :: Python :: 3
Classifier: Programming Language :: Python :: 3.8
Classifier: Programming Language :: Python :: 3.9
Classifier: Programming Language :: Python :: 3.10
Classifier: Topic :: Database :: Front-Ends
Classifier: Operating System :: OS Independent
Requires-Python: >=3.8
License-File: LICENSE
Requires-Dist: SQLAlchemy>=1.3
Provides-Extra: intersystems
Requires-Dist: intersystems-irispython==5.1.0; extra == "intersystems"
Dynamic: license-file
Dynamic: requires-dist
